deepseekr/__init__.py
deepseekr/deepseekr.py
deepseekr-0.3.0.dist-info/METADATA
deepseekr-0.3.0.dist-info/WHEEL
deepseekr-0.3.0.dist-info/top_level.txt
deepseekr-0.3.0.dist-info/RECORD
