Metadata-Version: 2.4
Name: deepseekr
Version: 0.3.0
Summary: Selenium DeepSeek automation, using Google Chrome.
Home-page: https://github.com/MYusufY/deepseekr
Author: Yusuf YILDIRIM
Author-email: yusuf@tachion.tech
Classifier: Programming Language :: Python :: 3
Classifier: Operating System :: OS Independent
Classifier: License :: OSI Approved :: MIT License
Classifier: Topic :: Internet :: Proxy Servers
Classifier: Topic :: System :: Networking
Requires-Python: >=3.8
Requires-Dist: selenium>=4.0.0
Requires-Dist: undetected-chromedriver>=3.0.0
Requires-Dist: markdownify>=0.11.6
Provides-Extra: dev
Requires-Dist: pytest; extra == "dev"
Requires-Dist: black; extra == "dev"
Requires-Dist: flake8; extra == "dev"
Dynamic: author
Dynamic: author-email
Dynamic: classifier
Dynamic: description
Dynamic: description-content-type
Dynamic: home-page
Dynamic: provides-extra
Dynamic: requires-dist
Dynamic: requires-python
Dynamic: summary
